Phi/__init__.py
Phi/finished_methods.py
Phi/phi.dll
DenemePack-0.0.7.dist-info/LICENSE
DenemePack-0.0.7.dist-info/METADATA
DenemePack-0.0.7.dist-info/WHEEL
DenemePack-0.0.7.dist-info/top_level.txt
DenemePack-0.0.7.dist-info/RECORD
